fmi/__init__.py
fmi/fmi.py
fmi/observation.py
fmi/symbols/1.svg
fmi/symbols/2.svg
fmi/symbols/21.svg
fmi/symbols/22.svg
fmi/symbols/23.svg
fmi/symbols/3.svg
fmi/symbols/31.svg
fmi/symbols/32.svg
fmi/symbols/33.svg
fmi/symbols/41.svg
fmi/symbols/42.svg
fmi/symbols/43.svg
fmi/symbols/51.svg
fmi/symbols/52.svg
fmi/symbols/53.svg
fmi/symbols/61.svg
fmi/symbols/62.svg
fmi/symbols/63.svg
fmi/symbols/64.svg
fmi/symbols/71.svg
fmi/symbols/72.svg
fmi/symbols/73.svg
fmi/symbols/81.svg
fmi/symbols/82.svg
fmi/symbols/83.svg
fmi/symbols/91.svg
fmi/symbols/92.svg
fmi/symbols/__init__.py
fmi_weather-1.3.0.dist-info/LICENSE
fmi_weather-1.3.0.dist-info/METADATA
fmi_weather-1.3.0.dist-info/WHEEL
fmi_weather-1.3.0.dist-info/top_level.txt
fmi_weather-1.3.0.dist-info/RECORD
