Metadata-Version: 2.1
Name: fmi-weather
Version: 1.3.0
Summary: FMI weather data fetcher
Home-page: https://github.com/kipe/fmi
Author: Kimmo Huoman
Author-email: kipenroskaposti@gmail.com
License-File: LICENSE
Requires-Dist: beautifulsoup4 (>=4.8.1)
Requires-Dist: python-dateutil (>=2.8.0)
Requires-Dist: requests (>=2.20.0)
